collectd_transmission/__init__.py
collectd_transmission-3.7.dist-info/licenses/LICENSE
collectd_transmission-3.7.dist-info/METADATA
collectd_transmission-3.7.dist-info/WHEEL
collectd_transmission-3.7.dist-info/top_level.txt
collectd_transmission-3.7.dist-info/RECORD
