Metadata-Version: 2.4
Name: collectd_transmission
Version: 3.7
Summary: A python plugin for collectd to get stats from a runnning transmission server
License: 'ISC'
Keywords: collectd,transmission,statistics
Classifier: Development Status :: 5 - Production/Stable
Classifier: Environment :: Console
Classifier: Intended Audience :: System Administrators
Classifier: License :: OSI Approved :: ISC License (ISCL)
Classifier: Natural Language :: English
Classifier: Programming Language :: Python :: 3
Classifier: Operating System :: POSIX
Classifier: Topic :: System :: Monitoring
Requires-Python: >=3.10
License-File: LICENSE
Requires-Dist: transmission-rpc>=4.3.1
Dynamic: license-file
